qualityforward/Map.py
qualityforward/Project.py
qualityforward/QualityForward.py
qualityforward/Tenant.py
qualityforward/TestCycle.py
qualityforward/TestPhase.py
qualityforward/TestResult.py
qualityforward/TestSuite.py
qualityforward/TestSuiteAssignment.py
qualityforward/TestSuiteVersion.py
qualityforward/User.py
qualityforward/__init__.py
qualityforward-1.1.dist-info/LICENSE
qualityforward-1.1.dist-info/METADATA
qualityforward-1.1.dist-info/WHEEL
qualityforward-1.1.dist-info/top_level.txt
qualityforward-1.1.dist-info/RECORD
