Metadata-Version: 2.1
Name: qualityforward
Version: 1.1
Summary: Python library for QualityForward API
Home-page: https://cloud.veriserve.co.jp/
Author: Atsushi Nakatsugawa
Author-email: atsushi@moongift.jp
License: UNKNOWN
Platform: UNKNOWN
Classifier: Programming Language :: Python :: 3.7
Classifier: License :: OSI Approved :: MIT License
Classifier: Operating System :: OS Independent
